devtools/scripts/create_conda_env.py
docs/scripts/gen_ref_pages.py
red/__init__.py
red/_exceptions.py
red/_validation.py
red/_version.py
red/confidence_intervals.py
red/equilibration.py
red/ess.py
red/gelman_rubin.py
red/plot.py
red/py.typed
red/sse.py
red/variance.py
red/data/example_times.npy
red/data/example_timeseries.npy
red/tests/__init__.py
red/tests/test_confidence_intervals.py
red/tests/test_equilibration.py
red/tests/test_ess.py
red/tests/test_gelman_rubin.py
red/tests/test_import.py
red/tests/test_plot.py
red/tests/test_sse.py
red/tests/test_validation.py
red/tests/test_variance.py
red_molsim-0.1.4.dist-info/licenses/LICENSE
red_molsim-0.1.4.dist-info/METADATA
red_molsim-0.1.4.dist-info/WHEEL
red_molsim-0.1.4.dist-info/top_level.txt
red_molsim-0.1.4.dist-info/RECORD
