Metadata-Version: 2.4
Name: red-molsim
Version: 0.1.4
Summary: Robust Equilibration Detection
Author-email: Finlay Clark <finlay.clark@ed.ac.uk>
License: MIT
Project-URL: Homepage, https://fjclark.github.io/red/latest/
Classifier: License :: OSI Approved :: MIT License
Classifier: Programming Language :: Python :: 3
Requires-Python: >=3.8
License-File: LICENSE
Requires-Dist: importlib-resources; python_version < "3.10"
Requires-Dist: numpy>=1.20.0
Requires-Dist: scipy>=1.6.0
Requires-Dist: matplotlib>=3.3.0
Requires-Dist: statsmodels>=0.12.0
Requires-Dist: numba>=0.52.0
Provides-Extra: dev
Requires-Dist: mypy; extra == "dev"
Requires-Dist: pytest>=6.1.2; extra == "dev"
Requires-Dist: pytest-runner; extra == "dev"
Requires-Dist: pytest-env; extra == "dev"
Requires-Dist: ruff; extra == "dev"
Requires-Dist: pre-commit; extra == "dev"
Requires-Dist: types-PyYAML; extra == "dev"
Requires-Dist: mkdocs; extra == "dev"
Requires-Dist: mkdocs-material; extra == "dev"
Requires-Dist: mkdocs-gen-files; extra == "dev"
Requires-Dist: mkdocs-literate-nav; extra == "dev"
Requires-Dist: mkdocs-jupyter; extra == "dev"
Requires-Dist: mkdocstrings; extra == "dev"
Requires-Dist: mkdocstrings-python; extra == "dev"
Requires-Dist: black; extra == "dev"
Requires-Dist: mike; extra == "dev"
Requires-Dist: mkdocs-bibtex; extra == "dev"
Requires-Dist: build; extra == "dev"
Requires-Dist: twine; extra == "dev"
Dynamic: license-file
